gatekit/__init__.py
gatekit/__main__.py
gatekit/_version.py
gatekit/main.py
gatekit/server_manager.py
gatekit/cli/__init__.py
gatekit/cli/startup_error_handler.py
gatekit/cli/startup_error_notifier.py
gatekit/config/__init__.py
gatekit/config/errors.py
gatekit/config/framework_fields.py
gatekit/config/json_schema.py
gatekit/config/loader.py
gatekit/config/models.py
gatekit/config/persistence.py
gatekit/config/schema_defs.py
gatekit/config/serialization.py
gatekit/core/routing.py
gatekit/diagnostics/README.md
gatekit/diagnostics/__init__.py
gatekit/diagnostics/collector.py
gatekit/plugins/__init__.py
gatekit/plugins/interfaces.py
gatekit/plugins/manager.py
gatekit/plugins/auditing/__init__.py
gatekit/plugins/auditing/base.py
gatekit/plugins/auditing/csv.py
gatekit/plugins/auditing/human_readable.py
gatekit/plugins/auditing/json_lines.py
gatekit/plugins/middleware/__init__.py
gatekit/plugins/middleware/call_trace.py
gatekit/plugins/middleware/tool_manager.py
gatekit/plugins/security/__init__.py
gatekit/plugins/security/pii.py
gatekit/plugins/security/prompt_injection.py
gatekit/plugins/security/secrets.py
gatekit/protocol/__init__.py
gatekit/protocol/errors.py
gatekit/protocol/messages.py
gatekit/protocol/validation.py
gatekit/proxy/__init__.py
gatekit/proxy/server.py
gatekit/proxy/stdio_server.py
gatekit/transport/__init__.py
gatekit/transport/base.py
gatekit/transport/errors.py
gatekit/transport/stdio.py
gatekit/tui/CLAUDE.md
gatekit/tui/TUI_DEBUG_TESTING_GUIDE.md
gatekit/tui/__init__.py
gatekit/tui/app.py
gatekit/tui/clipboard.py
gatekit/tui/config_adapter.py
gatekit/tui/constants.py
gatekit/tui/path_suggester.py
gatekit/tui/platform_paths.py
gatekit/tui/recent_files.py
gatekit/tui/terminal_info.py
gatekit/tui/debug/__init__.py
gatekit/tui/debug/logger.py
gatekit/tui/guided_setup/__init__.py
gatekit/tui/guided_setup/client_registry.py
gatekit/tui/guided_setup/config_generation.py
gatekit/tui/guided_setup/deduplication.py
gatekit/tui/guided_setup/detection.py
gatekit-0.1.0.dist-info/METADATA
gatekit-0.1.0.dist-info/WHEEL
gatekit-0.1.0.dist-info/entry_points.txt
gatekit-0.1.0.dist-info/licenses/LICENSE
gatekit-0.1.0.dist-info/licenses/NOTICE
gatekit-0.1.0.dist-info/RECORD
