Metadata-Version: 2.4
Name: gatekit
Version: 0.1.0
Summary: A hackable Model Context Protocol (MCP) gateway
Project-URL: Repository, https://github.com/gatekit-ai/gatekit
Project-URL: Documentation, https://github.com/gatekit-ai/gatekit/tree/main/docs
Project-URL: Bug Tracker, https://github.com/gatekit-ai/gatekit/issues
Author: Doug Bright
License: Apache-2.0
License-File: LICENSE
License-File: NOTICE
Keywords: audit-logging,gateway,llm,mcp,model-context-protocol,proxy,terminal,tui
Classifier: Development Status :: 3 - Alpha
Classifier: Environment :: Console
Classifier: Intended Audience :: Developers
Classifier: License :: OSI Approved :: Apache Software License
Classifier: Operating System :: OS Independent
Classifier: Programming Language :: Python :: 3
Classifier: Programming Language :: Python :: 3.10
Classifier: Programming Language :: Python :: 3.11
Classifier: Programming Language :: Python :: 3.12
Classifier: Programming Language :: Python :: 3.13
Classifier: Topic :: Security
Classifier: Topic :: Software Development :: Libraries
Requires-Python: >=3.10
Requires-Dist: anyio~=4.12.0
Requires-Dist: jsonschema~=4.25.0
Requires-Dist: pathspec==0.12.1
Requires-Dist: pydantic==2.11.5
Requires-Dist: pyyaml==6.0.2
Requires-Dist: textual-fspicker==0.6.0
Requires-Dist: textual~=7.2.0
Requires-Dist: tomli~=2.2.0; python_version < '3.11'
Provides-Extra: dev
Requires-Dist: black>=23.0; extra == 'dev'
Requires-Dist: mypy>=1.5; extra == 'dev'
Requires-Dist: pytest-asyncio>=0.21; extra == 'dev'
Requires-Dist: pytest-cov>=4.0; extra == 'dev'
Requires-Dist: pytest>=7.0; extra == 'dev'
Requires-Dist: ruff>=0.0.290; extra == 'dev'
